yarl/__init__.py
yarl/_parse.py
yarl/_path.py
yarl/_query.py
yarl/_quoters.py
yarl/_quoting.py
yarl/_quoting_c.cp310-win32.pyd
yarl/_quoting_c.pyi
yarl/_quoting_c.pyx
yarl/_quoting_py.py
yarl/_url.py
yarl/py.typed
yarl-1.18.2.dist-info/LICENSE
yarl-1.18.2.dist-info/METADATA
yarl-1.18.2.dist-info/NOTICE
yarl-1.18.2.dist-info/WHEEL
yarl-1.18.2.dist-info/top_level.txt
yarl-1.18.2.dist-info/RECORD
