Metadata-Version: 2.1
Name: yarl
Version: 1.18.2
Summary: Yet another URL library
Home-page: https://github.com/aio-libs/yarl
Author: Andrew Svetlov
Author-email: andrew.svetlov@gmail.com
Maintainer: aiohttp team <team@aiohttp.org>
Maintainer-email: team@aiohttp.org
License: Apache-2.0
Project-URL: Chat: Matrix, https://matrix.to/#/#aio-libs:matrix.org
Project-URL: Chat: Matrix Space, https://matrix.to/#/#aio-libs-space:matrix.org
Project-URL: CI: GitHub Workflows, https://github.com/aio-libs/yarl/actions?query=branch:master
Project-URL: Code of Conduct, https://github.com/aio-libs/.github/blob/master/CODE_OF_CONDUCT.md
Project-URL: Coverage: codecov, https://codecov.io/github/aio-libs/yarl
Project-URL: Docs: Changelog, https://yarl.aio-libs.org/en/latest/changes/
Project-URL: Docs: RTD, https://yarl.aio-libs.org
Project-URL: GitHub: issues, https://github.com/aio-libs/yarl/issues
Project-URL: GitHub: repo, https://github.com/aio-libs/yarl
Keywords: cython,cext,yarl
Classifier: Development Status :: 5 - Production/Stable
Classifier: Intended Audience :: Developers
Classifier: License :: OSI Approved :: Apache Software License
Classifier: Programming Language :: Cython
Classifier: Programming Language :: Python
Classifier: Programming Language :: Python :: 3
Classifier: Programming Language :: Python :: 3.9
Classifier: Programming Language :: Python :: 3.10
Classifier: Programming Language :: Python :: 3.11
Classifier: Programming Language :: Python :: 3.12
Classifier: Programming Language :: Python :: 3.13
Classifier: Topic :: Internet :: WWW/HTTP
Classifier: Topic :: Software Development :: Libraries :: Python Modules
Requires-Python: >=3.9
License-File: LICENSE
License-File: NOTICE
Requires-Dist: idna>=2.0
Requires-Dist: multidict>=4.0
Requires-Dist: propcache>=0.2.0
